CHANGELOG.md
pybas_automation/__init__.py
pybas_automation/bas_actions/__init__.py
pybas_automation/bas_actions/browser/__init__.py
pybas_automation/bas_actions/browser/browser_settings/__init__.py
pybas_automation/bas_actions/browser/browser_settings/models.py
pybas_automation/bas_actions/browser/proxy/__init__.py
pybas_automation/bas_actions/browser/proxy/models.py
pybas_automation/bas_actions/fingerprint_switcher/__init__.py
pybas_automation/bas_actions/fingerprint_switcher/apply_fingerprint/__init__.py
pybas_automation/bas_actions/fingerprint_switcher/apply_fingerprint/models.py
pybas_automation/browser_automator/__init__.py
pybas_automation/browser_automator/browser_automator.py
pybas_automation/browser_automator/cdp_client.py
pybas_automation/browser_automator/models.py
pybas_automation/browser_profile/__init__.py
pybas_automation/browser_profile/models.py
pybas_automation/browser_profile/proxy.py
pybas_automation/browser_profile/settings.py
pybas_automation/browser_profile/storage.py
pybas_automation/fingerprint/__init__.py
pybas_automation/fingerprint/fingerprint.py
pybas_automation/fingerprint/models.py
pybas_automation/proxy_providers/__init__.py
pybas_automation/proxy_providers/brightdata/__init__.py
pybas_automation/proxy_providers/brightdata/models.py
pybas_automation/settings.py
pybas_automation/task/__init__.py
pybas_automation/task/models.py
pybas_automation/task/settings.py
pybas_automation/task/storage.py
pybas_automation/utils/__init__.py
pybas_automation/utils/filesystem.py
pybas_automation/utils/logger.py
pybas_automation/utils/utils.py
pybas_automation-0.1.16.dist-info/LICENSE
pybas_automation-0.1.16.dist-info/METADATA
pybas_automation-0.1.16.dist-info/WHEEL
pybas_automation-0.1.16.dist-info/RECORD
