Metadata-Version: 2.1
Name: pybas-automation
Version: 0.1.16
Summary: A Python library for automating BrowserAutomationStudio (BAS) using headless Chromium browsers and Windows GUI program.
Home-page: https://github.com/sergerdn/py-bas-automation
License: MIT
Keywords: headless Chromium,Python browser automation,browser fingerprint protection,prevent browser fingerprinting
Author: sergerdn
Author-email: 64213648+sergerdn@users.noreply.github.com
Requires-Python: >=3.11,<4.0
Classifier: License :: OSI Approved :: MIT License
Classifier: Programming Language :: Python :: 3
Classifier: Programming Language :: Python :: 3.11
Classifier: Topic :: Internet :: WWW/HTTP :: Browsers
Classifier: Topic :: Software Development :: Libraries :: Python Modules
Requires-Dist: fastapi (>=0.104.0,<0.105.0)
Requires-Dist: filelock (>=3.12.4,<4.0.0)
Requires-Dist: httpx[socks] (>=0.25.0,<0.26.0)
Requires-Dist: pydantic (>=2.4.2,<3.0.0)
Requires-Dist: python-dotenv (>=1.0.0,<2.0.0)
Requires-Dist: websockets (>=11.0.3,<12.0.0)
Project-URL: Repository, https://github.com/sergerdn/py-bas-automation
